{
"RFyc" : ["#f5eb4e","#f5f3dc","#f5eb4e","#e67632","#dc3200","#f5eb4e","#dc651b","#b3aa97","#f6835a"],
"RFYy" : ["#dde740","#cabb52","#f6f57a","#dc8634","#de5711","#dbe53b","#dd7d26","#b3aa97","#f6835a"],
"RFYc" : ["#f5eb4e","#f5eb4e","#f5eb4e","#e67632","#dc3200","#f5eb4e","#dc651b","#b3aa97","#f6835a"],
"RFYv" : ["#b3bd61","#b9bd60","#cac472","#e06e30","#dc3200","#83c270","#d9631c","#b3aa97","#f6835a"],
"RFyy" : ["#e9e947","#dfd797","#f6f064","#e17e33","#dd4509","#e8e844","#dd7121","#b3aa97","#f6835a"],
"RFyv" : ["#e3e545","#f5f3dc","#f4f2d3","#e06e30","#dc3200","#bed356","#da641b","#b3aa97","#f6835a"],
"RFyCD" : ["#aab633","#869d39","#bec443","#df7230","#dc3200","#aab633","#515063","#533d08","#7e5318"],
"RFYYD" : ["#acb738","#a19944","#d4d677","#d88232","#de5711","#a9b533","#604418","#533d08","#a48c37"],
"RFYCD" : ["#5e8018","#508a30","#879c37","#d96e2e","#dc3200","#5e8018","#211b26","#533d08","#714a13"],
"RFYVD" : ["#497d45","#3e8651","#699558","#d96e2e","#dc3200","#4d7585","#211b26","#533d08","#714a13"],
"RFyYD" : ["#abb736","#949b3f","#c9cd5d","#db7a31","#dd4509","#a9b533","#938c6c","#533d08","#917028"],
"RFyVD" : ["#a5b239","#869d39","#bec443","#d96e2e","#dc3200","#7c8f7f","#515063","#533d08","#714a13"],
"RFyCd" : ["#97a431","#708631","#a6af3c","#de5d30","#dc3200","#97a431","#363648","#533d08","#7e5318"],
"RFYYd" : ["#929b3b","#888243","#b9bb71","#d27126","#de5711","#8f9936","#4e3815","#533d08","#a48c37"],
"RFYCd" : ["#486222","#456c35","#6a7d3c","#d3572e","#dc3200","#486222","#211b26","#533d08","#714a13"],
"RFYVd" : ["#2d7050","#2b7769","#418353","#d4542d","#dc3200","#386d9c","#211b26","#533d08","#714a13"],
"RFyYd" : ["#949f36","#7c843a","#b0b557","#d8672b","#dd4509","#939e34","#938c6c","#533d08","#917028"],
"RFyVd" : ["#93a139","#718732","#a6af3c","#de5830","#dc3200","#6c8691","#444356","#533d08","#714a13"],
"RFyCa" : ["#879332","#5e702e","#939c3a","#d23f2a","#dc3200","#879332","#2a293d","#533d08","#7e5318"],
"RFYYa" : ["#82851c","#6e6023","#aba74d","#cb6211","#de5711","#7f831a","#422c0b","#533d08","#a48c37"],
"RFYCa" : ["#37500e","#2f5b1c","#5c6f21","#c43c22","#b93e1b","#37500e","#211b26","#533d08","#714a13"],
"RFYVa" : ["#23604d","#1f6865","#32704c","#ca331f","#dc3200","#4b5aa4","#211b26","#533d08","#714a13"],
"RFyYa" : ["#848c27","#666828","#9fa244","#ce511d","#dd4509","#838b26","#8a8466","#533d08","#917028"],
"RFyVa" : ["#858f3c","#5e702e","#929c3a","#d43622","#dc3200","#7d729b","#363648","#533d08","#714a13"],
"rFyc" : ["#f5eb4e","#f6f4d8","#f6f3c4","#ebe5da","#ebe5da","#f4eb58","#ebe5da","#a19b8b","#fc6c2d"],
"rFYy" : ["#dde53c","#cab852","#f6f373","#d9dfe5","#d4dee9","#dce43d","#d5dfe1","#bbb29e","#e67346"],
"rFYc" : ["#f5eb4e","#f5eb4e","#f5eb4e","#ebe5da","#ebe5da","#f4eb58","#ebe5da","#b3aa97","#f6835a"],
"rFYv" : ["#b6bd60","#b9bd60","#cbc663","#dae0e5","#cddced","#8ec26f","#ccdced","#bfb6a1","#ff7c47"],
"rFyy" : ["#f5eb4e","#dae43b","#f6f3c4","#e4e3de","#e5e3dd","#f4eb58","#e1e2e0","#a19b8b","#fc6c2d"],
"rFyv" : ["#f4ea4e","#ebe5ae","#eae4a6","#dae0e5","#cddced","#b5d372","#dadfcd","#bfb6a1","#ff7c47"],
"rFyCD" : ["#a2b445","#5b831b","#bec447","#7198b2","#7b9ec5","#9db151","#515063","#665546","#6e5c49"],
"rFYYD" : ["#a6b345","#a29944","#c7cb83","#7494a7","#7f9cb9","#a1b050","#604418","#665324","#94832b"],
"rFYCD" : ["#5e8018","#508a30","#9cb74c","#4475a8","#4f7abd","#5b7f28","#211b26","#533d08","#432b13"],
"rFYVD" : ["#427f43","#3e8666","#5b9454","#4461a8","#4f66bd","#487187","#211b26","#533d08","#432b13"],
"rFyYD" : ["#b4bd5a","#5b831b","#c1c64a","#afbfc1","#b7c3ce","#b1bb5f","#938c6c","#665546","#6e5c49"],
"rFyVD" : ["#83b14a","#5a831b","#99c226","#729bb5","#7b9ec3","#638788","#515063","#533d08","#432b13"],
"rFyCd" : ["#8ba043","#527e2f","#9fb741","#6e8ead","#6c89af","#889f4f","#363648","#5f4f41","#72614d"],
"rFYYd" : ["#8f9936","#8a8b42","#b3b668","#5d7d90","#6a86a2","#8a9640","#4e3815","#665324","#917f28"],
"rFYCd" : ["#47650a","#47650a","#7d9f4a","#3962a0","#4267aa","#46661a","#211b26","#533d08","#483214"],
"rFYVd" : ["#2c7151","#2b7769","#3f8153","#384ea5","#4452b7","#4973a8","#211b26","#533d08","#432b13"],
"rFyYd" : ["#a4ad4b","#537e2f","#a2b942","#aab7b9","#afb9c5","#a2ac50","#938c6c","#5f4f41","#72614d"],
"rFyVd" : ["#6fa044","#527e2f","#7db42f","#7495b5","#6c89af","#5c83a9","#444356","#533d08","#432b13"],
"rFyCa" : ["#81943a","#617630","#9eac48","#6281a7","#6078a9","#7e9347","#2a293d","#5f4f41","#6d5b47"],
"rFYYa" : ["#7f831a","#706823","#a4a245","#566d7a","#61768b","#7a8124","#422c0b","#533d08","#8f7e27"],
"rFYCa" : ["#3c560b","#3f5e10","#769035","#3b50a2","#4e5cb1","#3e581c","#211b26","#533d08","#483214"],
"rFYVa" : ["#1e5f4e","#1f6067","#306f53","#333b97","#3c3ca8","#4961af","#211b26","#533d08","#432b13"],
"rFyYa" : ["#81943a","#617630","#9eac48","#a0aeb7","#a5aec1","#7f9340","#8a8466","#5f4f41","#6d5b47"],
"rFyVa" : ["#58892c","#617630","#7bac28","#6887ae","#6078aa","#5770ae","#363648","#533d08","#432b13"],
"Rbyc" : ["#e7edb7","#cedda3","#f1f1be","#fac4a5","#e78051","#e7edb7","#f3d1a3","#b3aa97","#f28f63"],
"RbYy" : ["#c4dbb4","#c8d3b6","#dae9ca","#f4c8a0","#ea965a","#c3dab3","#eadcbd","#b3aa97","#f28f63"],
"RbYc" : ["#e1e593","#dee0a3","#e9eb9f","#fbaf80","#e78051","#e1e593","#e9bb8c","#b3aa97","#f28f63"],
"RbYv" : ["#b6d0b4","#bcc9b2","#cfe3c6","#f7b691","#e78051","#99b1cb","#fbac7e","#b3aa97","#f28f63"],
"Rbyy" : ["#d5e4b5","#cbd8ad","#e5edc4","#f7c6a2","#e98b56","#d5e3b5","#eed7b0","#b3aa97","#f28f63"],
"Rbyv" : ["#e1ecb8","#cedda3","#f1f1be","#f6b48b","#e78051","#a8dfc2","#fdad7e","#b3aa97","#f28f63"],
"RbyCD" : ["#8ac029","#69a334","#a0ce39","#f3af7f","#e78051","#8ac029","#515063","#533d08","#87771c"],
"RbYYD" : ["#aabe80","#abb181","#cdd8a6","#eeac71","#ea965a","#a8bd7e","#604418","#533d08","#b7a62c"],
"RbYCD" : ["#18806f","#317c88","#3a9c7d","#eca77e","#e78051","#18806f","#211b26","#533d08","#7b6d17"],
"RbYVD" : ["#3a7888","#385f89","#549998","#ec9f70","#e78051","#426db6","#211b26","#533d08","#7b6d17"],
"RbyYD" : ["#9abf55","#8aaa5b","#b7d370","#f0ad78","#e98b56","#99be54","#938c6c","#533d08","#9f8f24"],
"RbyVD" : ["#2c997a","#058379","#4bba68","#ee9f6f","#e78051","#3b7daf","#515063","#533d08","#7b6d17"],
"RbyCd" : ["#81a524","#5a8227","#90b12f","#eda577","#e78051","#81a524","#363648","#533d08","#87771c"],
"RbYYd" : ["#8a9a68","#8c9169","#abb48b","#e9a76e","#ea965a","#889966","#4e3815","#533d08","#b7a62c"],
"RbYCd" : ["#076958","#1c636f","#217d60","#e3a078","#e78051","#076958","#211b26","#533d08","#7b6d17"],
"RbYVd" : ["#275e79","#25437a","#3d7b85","#ec9e70","#e78051","#385fae","#211b26","#533d08","#7b6d17"],
"RbyYd" : ["#869f46","#738a48","#9eb35d","#eba672","#e98b56","#859f45","#938c6c","#533d08","#9f8f24"],
"RbyVd" : ["#217b71","#1e6a9c","#419b59","#eea06f","#e78051","#356eaa","#444356","#533d08","#7b6d17"],
"RbyCa" : ["#48760e","#447a24","#5e841d","#eba87c","#e78051","#48760e","#2a293d","#533d08","#87771c"],
"RbYYa" : ["#778658","#636748","#7c8362","#e6a46b","#ea965a","#768656","#422c0b","#533d08","#b7a62c"],
"RbYCa" : ["#074b55","#173c59","#206b66","#e49e79","#e78051","#074b55","#211b26","#533d08","#7b6d17"],
"RbYVa" : ["#12466a","#091e67","#266574","#ec9e70","#e78051","#2e53a7","#211b26","#533d08","#7b6d17"],
"RbyYa" : ["#48760e","#447a24","#5e841d","#eba87c","#e78051","#48760e","#8a8466","#533d08","#87771c"],
"RbyVa" : ["#107063","#005e7c","#35974b","#eba170","#e78051","#2c67a4","#363648","#533d08","#7b6d17"],
"rbyc" : ["#eae5b3","#f5f3d5","#f4f2d3","#ebe5da","#ebe5da","#eae5b3","#ebe5da","#a19b8b","#fc6c2d"],
"rbYy" : ["#c3dab3","#c5d6b7","#dfeac2","#d9dfe5","#d4dee9","#c3dab3","#d2dde2","#bbb29e","#e67346"],
"rbYc" : ["#e1e593","#dee0a0","#e1e593","#ebe5da","#ebe5da","#e1e593","#eae5d9","#b3aa97","#f6835a"],
"rbYv" : ["#b5d0b1","#bccab2","#cfe3c6","#dae0e5","#cddced","#93b2c6","#cedbeb","#bfb6a1","#ff7c47"],
"rbyy" : ["#eae5b3","#dfeeb2","#f4f2d3","#dbe0e4","#dbe0e4","#eae5b3","#dbe0e4","#a19b8b","#fc6c2d"],
"rbyv" : ["#e7e4b5","#f5f3d6","#f3f1d1","#d7dfe6","#cddced","#add5df","#cedceb","#bfb6a1","#ff7c47"],
"rbyCD" : ["#7dba35","#4ea934","#9bca38","#7198b2","#7b9ec5","#7bb643","#515063","#665546","#948e59"],
"rbYYD" : ["#a7b788","#aab181","#c9d5a9","#7494a7","#7f9cb9","#a1b38c","#604418","#665324","#b3a428"],
"rbYCD" : ["#18806f","#317c88","#3ba084","#4475a8","#4f7abd","#1c7f76","#211b26","#533d08","#432b13"],
"rbYVD" : ["#2a6b8d","#335ba1","#5091a2","#4461a8","#4f66bd","#4a64c1","#211b26","#533d08","#432b13"],
"rbyYD" : ["#9bb871","#79ad58","#afcd6e","#a7bac3","#aebece","#98b675","#938c6c","#665546","#948e59"],
"rbyVD" : ["#3e99ad","#26a9bc","#43b1c1","#5a78bb","#677bc6","#6084d0","#515063","#533d08","#432b13"],
"rbyCd" : ["#72a403","#41881d","#80b62f","#6e8ead","#6c89af","#72a316","#363648","#5f4f41","#948e59"],
"rbYYd" : ["#8b9773","#8b8f70","#abb299","#5d7d90","#6a86a2","#869477","#4e3815","#665324","#afa125"],
"rbYCd" : ["#076958","#1a5e6c","#2d876e","#3962a0","#4267aa","#0c6a61","#211b26","#533d08","#483214"],
"rbYVd" : ["#0d4e7b","#26417a","#26718e","#384ea5","#4452b7","#3d5ec6","#211b26","#533d08","#432b13"],
"rbyYd" : ["#8da35e","#5d823b","#95b365","#a3b3bf","#a3b1c1","#8ba263","#938c6c","#5f4f41","#948e59"],
"rbyVd" : ["#248cab","#109ab1","#31a8bd","#5267b6","#5e6ac1","#567bd2","#515063","#533d08","#432b13"],
"rbyCa" : ["#458513","#447922","#5f9612","#6281a7","#6078a9","#488624","#2a293d","#5f4f41","#978f5d"],
"rbYYa" : ["#798561","#5b6148","#929980","#566d7a","#61768b","#758264","#422c0b","#533d08","#b0a226"],
"rbYCa" : ["#084b53","#1e4247","#29695a","#3b50a2","#4e5cb1","#074b55","#211b26","#533d08","#483214"],
"rbYVa" : ["#164077","#1e278f","#22608c","#333b97","#3c3ca8","#3843bf","#211b26","#533d08","#432b13"],
"rbyYa" : ["#728c53","#4f6e34","#789748","#9aaabb","#9aa6bd","#718c59","#8a8466","#5f4f41","#978f5d"],
"rbyVa" : ["#0a5c83","#1a79a0","#17759b","#2e399d","#3c3ca8","#3747c1","#363648","#533d08","#432b13"],
"Rwyc" : ["#e6f0c1","#d0e2af","#eff3c7","#f0d3bc","#f4e7dd","#e6f0c1","#f3e6dc","#b3aa97","#f28f63"],
"RwYy" : ["#cbdfbf","#ced8bf","#deebd1","#eddbc1","#efe4d0","#cadebe","#f3e5d2","#b3aa97","#f28f63"],
"RwYc" : ["#dee6a6","#dde2b2","#e5ebb0","#f2d3bb","#f2e3ce","#dee6a6","#f2e1cd","#b3aa97","#f28f63"],
"RwYv" : ["#b7d2ad","#bccca9","#cde1bc","#f2ddc7","#f1dac3","#a4c0c9","#f7e7d5","#b3aa97","#f28f63"],
"Rwyy" : ["#d8e7c0","#cfddb7","#e6efcc","#eed7bf","#f1e5d6","#d8e7bf","#f3e5d7","#b3aa97","#f28f63"],
"Rwyv" : ["#e2edc3","#d0e2af","#eff3c7","#f7e1cb","#f7dfc7","#bbced6","#f8e7d5","#b3aa97","#f28f63"],
"RwyCD" : ["#bbd75c","#a8c671","#c5df63","#edd1b5","#e6bf99","#bbd75c","#515063","#533d08","#a09545"],
"RwYYD" : ["#a2c18f","#a5b68f","#c4d9b1","#e7d6ba","#e7cda8","#a1c08e","#604418","#533d08","#8bb657"],
"RwYCD" : ["#4baaa9","#5b94ab","#63bdaf","#edd1bb","#f2cdb5","#4baaa9","#211b26","#533d08","#948b40"],
"RwYVD" : ["#5781a7","#5163a4","#6e9fb5","#e8dac5","#f2cbb2","#5171c6","#211b26","#533d08","#948b40"],
"RwyYD" : ["#aecc76","#a6be80","#c4dc8a","#ead4b8","#e7c6a1","#aecb75","#938c6c","#533d08","#95a64e"],
"RwyVD" : ["#66acbc","#749bbd","#7bc2c1","#edddcb","#f2cbb2","#5987d1","#515063","#533d08","#948b40"],
"RwyCd" : ["#8ba84d","#8dab69","#95b054","#e6d0bb","#e6bf99","#8ba84d","#363648","#533d08","#a09545"],
"RwYYd" : ["#8c9d81","#8c967f","#a7b39d","#e6d4b9","#e7cda8","#8b9c80","#4e3815","#533d08","#8bb657"],
"RwYCd" : ["#3c7b6f","#4b7981","#4f8a78","#edcfb9","#f2cdb5","#3c7b6f","#211b26","#533d08","#948b40"],
"RwYVd" : ["#376eb8","#3241b6","#4f92c3","#e7dcc6","#f2cbb2","#4167ce","#211b26","#533d08","#948b40"],
"RwyYd" : ["#8ca267","#8ca074","#9eb279","#e6d2ba","#e7c6a1","#8ba267","#938c6c","#533d08","#95a64e"],
"RwyVd" : ["#49a1c8","#4478c7","#5ec1d2","#e8ddc5","#f2cbb2","#4a82d6","#444356","#533d08","#948b40"],
"RwyCa" : ["#6a8945","#7a9a64","#74914c","#dfd5c8","#e6bf99","#6a8945","#2a293d","#533d08","#a09545"],
"RwYYa" : ["#7f8a78","#797f72","#9fa799","#e5d2b8","#e7cda8","#7d8976","#422c0b","#533d08","#8bb657"],
"RwYCa" : ["#415550","#4a5c5f","#51655e","#edceb8","#f2cdb5","#415550","#211b26","#533d08","#948b40"],
"RwYVa" : ["#2f478a","#2f2d89","#426391","#e7dac5","#f2cbb2","#3c53b7","#211b26","#533d08","#948b40"],
"RwyYa" : ["#758a5f","#798c6b","#8a9c73","#e2d3c0","#e7c6a1","#74895e","#8a8466","#533d08","#95a64e"],
"RwyVa" : ["#2f478a","#2f2d89","#426391","#e7dac5","#f2cbb2","#3c53b7","#363648","#533d08","#948b40"],
"rwyc" : ["#e5efc0","#f5f3d5","#f3f2d3","#ebe5da","#ebe5da","#e5eec0","#e9e5d7","#a19b8b","#fc6c2d"],
"rwYy" : ["#cadebe","#cdd8bf","#dde9d1","#d9dfe5","#d4dee9","#cadebe","#d1dde1","#bbb29e","#e67346"],
"rwYc" : ["#e7edbb","#e7edbb","#e7edbb","#ebe5da","#ebe5da","#e7edbb","#e7e5d5","#b3aa97","#f6835a"],
"rwYv" : ["#c2d7ba","#bccca8","#d4e6c4","#dae0e5","#cddced","#94b3c7","#cedbeb","#bfb6a1","#ff7c47"],
"rwyy" : ["#e7edbb","#f5f3d6","#f4f3d5","#dbe0e4","#dbe0e4","#e7edbb","#dbe0e4","#a19b8b","#fc6c2d"],
"rwyv" : ["#e2edc1","#f5f3d6","#f3f2d3","#dae0e5","#cddced","#a8c4cf","#cedbeb","#bfb6a1","#ff7c47"],
"rwyCD" : ["#b5d75a","#abc86f","#cae174","#769eb6","#7b9ec5","#aed064","#515063","#665546","#8c9380"],
"rwYYD" : ["#aec3a0","#a3b58f","#c7d4bd","#7494a7","#7f9cb9","#a8bea2","#65502f","#665324","#98b4ad"],
"rwYCD" : ["#4baaa9","#5b94ab","#61bbad","#4377b1","#4f7abd","#49a4aa","#211b26","#533d08","#6a5a35"],
"rwYVD" : ["#597ba8","#5163a4","#6696ba","#4361b0","#4f66bd","#5f67c3","#211b26","#533d08","#6a5a35"],
"rwyYD" : ["#b8ce96","#cce9b9","#c9e5b4","#a7bac3","#aebece","#b4cb98","#938c6c","#665546","#9bb5ad"],
"rwyVD" : ["#8293bd","#7c81ba","#8ca7cb","#717cc4","#7a80cd","#8c87d2","#5c5b6d","#533d08","#6a5a35"],
"rwyCd" : ["#8aa84c","#8cab66","#a0bc65","#6e8ead","#6c89af","#87a657","#363648","#5f4f41","#8c9380"],
"rwYYd" : ["#929b8d","#7a8673","#a9b5a1","#5d7d90","#6a86a2","#8c988e","#52442d","#665324","#98b4ad"],
"rwYCd" : ["#457e7a","#41767f","#48938c","#3962a0","#4267aa","#447d7f","#211b26","#533d08","#6f6137"],
"rwYVd" : ["#3665b6","#3033c0","#5b7dd6","#384ea5","#4452b7","#5b64db","#211b26","#533d08","#6a5a35"],
"rwyYd" : ["#a2b38d","#96af81","#b0c696","#a3b3bf","#a4b2c3","#a0b097","#938c6c","#5f4f41","#9bb5ad"],
"rwyVd" : ["#6579cb","#705fd3","#818be3","#6669bd","#736fcb","#8c81e7","#515063","#533d08","#6a5a35"],
"rwyCa" : ["#5e823d","#789760","#7c9758","#6281a7","#6078a9","#5e8349","#2a293d","#5f4f41","#8b9180"],
"rwYYa" : ["#6e756a","#60695d","#939890","#566d7a","#61768b","#6b746c","#473b29","#533d08","#95b2ad"],
"rwYCa" : ["#344e4a","#45594c","#4e645c","#3b50a2","#4e5cb1","#324e4a","#211b26","#533d08","#6f6137"],
"rwYVa" : ["#2e3e88","#3f2d89","#4f63bf","#30379e","#3c3ca8","#5147c7","#211b26","#533d08","#6a5a35"],
"rwyYa" : ["#7c8c70","#90ab80","#8da67e","#9baabe","#9aa6bd","#7a8c74","#8a8466","#5f4f41","#98b4ad"],
"rwyVa" : ["#2e3e88","#3f2d89","#4f63bf","#30379e","#3c3ca8","#5147c7","#363648","#533d08","#6a5a35"]
}
